{"name":"Portfolio","tagline":"This file gives an overview of my capacities on different Web-technologies","body":"### Overview\r\n**Congratulations !**   \r\nYou just reach my portfolio. I can't figure all my project in there as some are confidential (the struggle is real !) and some are just unfinished).  \r\nIf you wanna test my algorithmic competence here is another challenge : find me on http://codingame.com/ ;).  \r\n\r\n\r\n### Contact\r\nYou can furthermore contact me directly through github here (@kylejumpen).\r\n\r\n### Support or Contact\r\nHaving trouble with Pages? Check out our [documentation](https://help.github.com/pages) or [contact support](https://github.com/contact) and we’ll help you sort it out.  \r\n\r\n**Enjoy !**\r\n","google":"","note":"Don't delete this file! It's used internally to help with page regeneration."}